pydecos/__init__.py
pydecos-0.0.2.dist-info/METADATA
pydecos-0.0.2.dist-info/WHEEL
pydecos-0.0.2.dist-info/top_level.txt
pydecos-0.0.2.dist-info/RECORD
