Metadata-Version: 2.1
Name: pydecos
Version: 0.0.2
Summary: The set of useful decorators.
Home-page: https://github.com/c-pher/pydecos.git
Author: Andrey Komissarov
Author-email: a.komisssarov@gmail.com
License: MIT
Platform: UNKNOWN
Classifier: Programming Language :: Python :: 3
Classifier: License :: OSI Approved :: MIT License
Classifier: Operating System :: OS Independent
Classifier: Intended Audience :: System Administrators
Classifier: Intended Audience :: Developers
Classifier: Natural Language :: English
Classifier: Programming Language :: Python :: 3.6
Classifier: Topic :: System :: Systems Administration
Classifier: Topic :: Software Development :: Libraries :: Python Modules
Requires-Python: >=3.6
